{
  "title": "Sprachbausteine Teil 1 - Exam 3: Liebe Vanessa",
  "skill": "sprach1",
  "type": "sprach1",
  "text": "Liebe Vanessa,\ndanke für deinen Brief, ⌄ __ (1) __ ⌄ ich mich total gefreut habe. Du fragst dich bestimmt, warum du schon drei Wochen ⌄ __ (2) __ ⌄ von mir gehört hast, oder? Ich war mit meiner Gastfamilie in Urlaub. Vierzehn Tage im Allgäu – mit den Kindern Stefan, Anja und Karina. Du weißt ⌄ __ (3) __ ⌄ selbst, wie anstrengend es ist, wenn man ständig drei kleine Kinder um sich hat, die pausenlos unterhalten werden möchten. ⌄ __ (4) __ ⌄ ist es übrigens in deiner Au-pair-Familie mit der kleinen Dorothea?\nDas Allgäu liegt in Süddeutschland am Fuß ⌄ __ (5) __ ⌄ Alpen. Wir sind fast jeden Tag gewandert, immer bergauf und bergab. Den Kindern und mir haben ständig die Füße weh ⌄ __ (6) __ ⌄, doch meine Gasteltern, Herr und Frau Zimmer, sind einfach immer weitergelaufen. Die Deutschen lieben es nämlich, in der Natur spazieren zu gehen, bis sie vor Erschöpfung ⌄ __ (7) __ ⌄.\nUnterwegs haben wir manchmal an einer sogenannten \"Wassertretstelle\" Rast gemacht. Das sind kleine Wasserbecken, die oft mitten im Wald liegen. Durch das Becken fließt ein Bach mit eiskaltem Wasser, das direkt von den Bergen kommt. Stell ⌄ __ (8) __ ⌄ vor, alle Wanderer ziehen ihre Schuhe und Strümpfe aus und laufen durch dieses Becken. Als ich meinen Fuß in dieses kalte Wasser getaucht hatte, dachte ich, dass ich gleich sterben muss.\nAm Wochenende haben wir alle Minigolf gespielt. Dabei muss ein Golfball mit einem Schläger in ein etwa zehn Meter entferntes Loch geschlagen werden. Aber vor dem Loch gibt es ⌄ __ (9) __ ⌄ Menge Hindernisse: Gräben, kleine Hügel, Tunnel. Der Spieler, dessen Ball mit den wenigsten Schlägen im Loch ankommt, hat gewonnen. Die Kinder wollten gar nicht mehr ⌄ __ (10) __ ⌄ aufhören.\nJetzt muss ich aber Schluss machen, die Kinder warten auf ihr Abendessen, denn die Zimmers sind heute nicht da: Sie wandern mal wieder.\nViele Grüße\ndeine Mercedes",
  "options": [
    {
      "id": 1,
      "options": ["an den", "auf dem", "über den"],
      "correct": 2,
      "highlight": {
        "connector": "über den",
        "before": "deinen Brief",
        "after": "ich mich",
        "highlightWords": ["deinen", "Brief", "über", "den", "ich", "mich"],
        "color": "#4CAF50",
        "helpKey": "sprach1_exam3_q1"
      }
    },
    {
      "id": 2,
      "options": ["nichts mehr", "noch nicht", "keines"],
      "correct": 0,
      "highlight": {
        "connector": "nichts mehr",
        "before": "drei Wochen",
        "after": "von mir",
        "highlightWords": ["drei", "Wochen", "nichts", "mehr", "von", "mir"],
        "color": "#FF9800",
        "helpKey": "sprach1_exam3_q2"
      }
    },
    {
      "id": 3,
      "options": ["doch", "eben", "überhaupt"],
      "correct": 0,
      "highlight": {
        "connector": "doch",
        "before": "Du weißt",
        "after": "selbst wie",
        "highlightWords": ["Du", "weißt", "doch", "selbst", "wie"],
        "color": "#2196F3",
        "helpKey": "sprach1_exam3_q3"
      }
    },
    {
      "id": 4,
      "options": ["Wann", "Was", "Wie"],
      "correct": 2,
      "highlight": {
        "connector": "Wie",
        "before": "übrigens",
        "after": "ist es",
        "highlightWords": ["übrigens", "Wie", "ist", "es"],
        "color": "#9C27B0",
        "helpKey": "sprach1_exam3_q4"
      }
    },
    {
      "id": 5,
      "options": ["der", "die", "von"],
      "correct": 0,
      "highlight": {
        "connector": "der",
        "before": "Fuß",
        "after": "Alpen. Wir",
        "highlightWords": ["Fuß", "der", "Alpen", "."],
        "color": "#F44336",
        "helpKey": "sprach1_exam3_q5"
      }
    },
    {
      "id": 6,
      "options": ["gelaufen", "getan", "geworden"],
      "correct": 1,
      "highlight": {
        "connector": "getan",
        "before": "die Füße weh",
        "after": ", doch meine",
        "highlightWords": ["die", "Füße", "weh", "getan", ",", "doch", "meine"],
        "color": "#00BCD4",
        "helpKey": "sprach1_exam3_q6"
      }
    },
    {
      "id": 7,
      "options": ["durchfallen", "umfallen", "wegfallen"],
      "correct": 1,
      "highlight": {
        "connector": "umfallen",
        "before": "Erschöpfung",
        "after": ". Unterwegs haben",
        "highlightWords": ["Erschöpfung", "umfallen", ".", "Unterwegs", "haben"],
        "color": "#8BC34A",
        "helpKey": "sprach1_exam3_q7"
      }
    },
    {
      "id": 8,
      "options": ["dich", "dir", "mal"],
      "correct": 1,
      "highlight": {
        "connector": "dir",
        "before": "Stell",
        "after": "vor, alle",
        "highlightWords": ["Stell", "dir", "vor", ",", "alle"],
        "color": "#FF5722",
        "helpKey": "sprach1_exam3_q8"
      }
    },
    {
      "id": 9,
      "options": ["alle", "ganze", "jede"],
      "correct": 2,
      "highlight": {
        "connector": "jede",
        "before": "gibt es",
        "after": "Menge Hindernisse",
        "highlightWords": ["gibt", "es", "jede", "Menge", "Hindernisse"],
        "color": "#3F51B5",
        "helpKey": "sprach1_exam3_q9"
      }
    },
    {
      "id": 10,
      "options": ["dabei", "damit", "davon"],
      "correct": 1,
      "highlight": {
        "connector": "damit",
        "before": "mehr",
        "after": "aufhören. Jetzt",
        "highlightWords": ["mehr", "damit", "aufhören", ".", "Jetzt"],
        "color": "#E91E63",
        "helpKey": "sprach1_exam3_q10"
      }
    }
  ]
}